clear/__init__.py
clear/__main__.py
clear/clear.py
clear/database.py
clear/epguides.py
clear/extract.py
clear/renamer.py
clear/tvfile.py
clear/util.py
clear-1.0.1.dist-info/DESCRIPTION.rst
clear-1.0.1.dist-info/METADATA
clear-1.0.1.dist-info/RECORD
clear-1.0.1.dist-info/WHEEL
clear-1.0.1.dist-info/metadata.json
clear-1.0.1.dist-info/top_level.txt
