Metadata-Version: 1.0
Name: clear
Version: 1.0.1
Summary: CLEAR: Command-line extract and rename utility
Home-page: http://github.com/davgeo/clear
Author: David George
Author-email: dcg.git@gmail.com
License: MIT
Platform: UNKNOWN
